{
    "type": "FeatureCollection",
    "features": [
        {
            "geometry": {
                "type": "Polygon",
                "coordinates": [
                    [
                        [
                            11.525942823931521,
                            9.591973003538346
                        ],
                        [
                            11.618443636429014,
                            9.420200371624292
                        ],
                        [
                            11.64283491468485,
                            9.397437070713863
                        ],
                        [
                            11.676631301975734,
                            9.391365154661116
                        ],
                        [
                            11.709497511728568,
                            9.381469112115719
                        ],
                        [
                            11.767271762031013,
                            9.330102521524903
                        ],
                        [
                            11.801688266655797,
                            9.257884839639365
                        ],
                        [
                            11.82029178147161,
                            9.228635932425426
                        ],
                        [
                            11.830110304002009,
                            9.197655968047963
                        ],
                        [
                            11.825459425715042,
                            9.162877712682311
                        ],
                        [
                            11.825769484100807,
                            9.127763579865487
                        ],
                        [
                            11.86059939761241,
                            9.069601636629477
                        ],
                        [
                            11.923644645755251,
                            9.039319259138264
                        ],
                        [
                            11.965399203867317,
                            8.988237160887444
                        ],
                        [
                            11.971497022297964,
                            8.918990680305894
                        ],
                        [
                            11.871038038338144,
                            8.71269837578686
                        ],
                        [
                            11.863493281412447,
                            8.643452184644476
                        ],
                        [
                            11.868660922497147,
                            8.606890886853837
                        ],
                        [
                            11.859255813050835,
                            8.573869813706144
                        ],
                        [
                            11.792179803143226,
                            8.519351123613372
                        ],
                        [
                            11.533797641954408,
                            8.211462944014459
                        ],
                        [
                            11.468375276703423,
                            8.15361101216499
                        ],
                        [
                            11.41349490760661,
                            8.089635785418437
                        ],
                        [
                            11.404296502705948,
                            8.058449108512123
                        ],
                        [
                            11.447808058916314,
                            7.951504772521321
                        ],
                        [
                            11.487908968918532,
                            7.880268531144105
                        ],
                        [
                            11.51519412583767,
                            7.852208390754079
                        ],
                        [
                            11.54785363014641,
                            7.84897850487354
                        ],
                        [
                            11.57410525909235,
                            7.871793798568425
                        ],
                        [
                            11.596326124823257,
                            7.898587941273278
                        ],
                        [
                            11.615756463093131,
                            7.929335396604362
                        ],
                        [
                            11.647692498242574,
                            7.943572310091859
                        ],
                        [
                            11.683039178902703,
                            7.927630175535992
                        ],
                        [
                            11.70784386657519,
                            7.897709494045804
                        ],
                        [
                            11.804995557914742,
                            7.806448919837569
                        ],
                        [
                            11.853157992990269,
                            7.691572110316903
                        ],
                        [
                            11.853054639736296,
                            7.624677026231845
                        ],
                        [
                            11.865663689989326,
                            7.558091980895159
                        ],
                        [
                            11.89046837696847,
                            7.5048394155751454
                        ],
                        [
                            11.902560661961795,
                            7.454377361802737
                        ],
                        [
                            11.903180780711972,
                            7.4538606280608795
                        ],
                        [
                            11.903545283289597,
                            7.4535568967742085
                        ],
                        [
                            11.844733926515245,
                            7.396397131636975
                        ],
                        [
                            11.782722208722051,
                            7.304516461929384
                        ],
                        [
                            11.762465047234812,
                            7.2855512812617
                        ],
                        [
                            11.744585001519683,
                            7.272167125625332
                        ],
                        [
                            11.736626830977999,
                            7.263278703950925
                        ],
                        [
                            11.74241459230362,
                            7.2574393119271825
                        ],
                        [
                            11.766185750048695,
                            7.252943427698567
                        ],
                        [
                            11.780241739702037,
                            7.241057799889237
                        ],
                        [
                            11.829954467921096,
                            7.169382619071902
                        ],
                        [
                            11.868918496523365,
                            7.127111241921173
                        ],
                        [
                            11.881320842448625,
                            7.102048301285876
                        ],
                        [
                            11.872225789373008,
                            7.079362335952998
                        ],
                        [
                            11.862613972876144,
                            7.075434858705227
                        ],
                        [
                            11.854139037945394,
                            7.077811984363317
                        ],
                        [
                            11.845147339351978,
                            7.081946155125743
                        ],
                        [
                            11.833985229912082,
                            7.082979622709099
                        ],
                        [
                            11.8203426505397,
                            7.078793778568429
                        ],
                        [
                            11.808870484290438,
                            7.071920918701695
                        ],
                        [
                            11.76639245639309,
                            7.033525344531412
                        ],
                        [
                            11.75150964313727,
                            7.0239651684212605
                        ],
                        [
                            11.74861576364378,
                            7.014973399471057
                        ],
                        [
                            11.746858764466056,
                            7.005361700157206
                        ],
                        [
                            11.741071003511436,
                            6.9975067455348245
                        ],
                        [
                            11.734249715510863,
                            6.995078096669436
                        ],
                        [
                            11.71864343271861,
                            6.994457865894563
                        ],
                        [
                            11.707481323756786,
                            6.9918223732937275
                        ],
                        [
                            11.697249389379103,
                            6.992855991110164
                        ],
                        [
                            11.692495157837493,
                            6.991615679773079
                        ],
                        [
                            11.688464395683575,
                            6.986913101749334
                        ],
                        [
                            11.684847045828837,
                            6.973838985471787
                        ],
                        [
                            11.681126342885882,
                            6.96861967362728
                        ],
                        [
                            11.623248739180445,
                            6.9322911840894
                        ],
                        [
                            11.561753784279109,
                            6.876067240827161
                        ],
                        [
                            11.54366703325466,
                            6.850694108416715
                        ],
                        [
                            11.538085977774202,
                            6.823899807682377
                        ],
                        [
                            11.54459720864352,
                            6.80893946236063
                        ],
                        [
                            11.566611369382244,
                            6.784186560459825
                        ],
                        [
                            11.5714689544438,
                            6.766229008657761
                        ],
                        [
                            11.568885132098247,
                            6.739098830569397
                        ],
                        [
                            11.562373900544886,
                            6.712485386196556
                        ],
                        [
                            11.533435099022148,
                            6.645099389319298
                        ],
                        [
                            11.509767293906698,
                            6.6123106748612575
                        ],
                        [
                            11.482585489850216,
                            6.597169472237333
                        ],
                        [
                            11.443104695377524,
                            6.593267981570739
                        ],
                        [
                            11.41674971473453,
                            6.572003032313754
                        ],
                        [
                            11.401763550012351,
                            6.538180849888972
                        ],
                        [
                            11.395665731287885,
                            6.49673639255314
                        ],
                        [
                            11.389361206241887,
                            6.473921241546793
                        ],
                        [
                            11.369827515369106,
                            6.455756995501191
                        ],
                        [
                            11.344196004332465,
                            6.443122101975248
                        ],
                        [
                            11.319494669655137,
                            6.4372825589054115
                        ],
                        [
                            11.308539266374208,
                            6.437902789730893
                        ],
                        [
                            11.286835165291077,
                            6.443225448743886
                        ],
                        [
                            11.275879760924099,
                            6.444207243045954
                        ],
                        [
                            11.272159057782135,
                            6.442036810691116
                        ],
                        [
                            11.26151371346939,
                            6.432554294023176
                        ],
                        [
                            11.25551924653367,
                            6.429970324377727
                        ],
                        [
                            11.248284546096826,
                            6.431003942278652
                        ],
                        [
                            11.237122437322165,
                            6.438057809883946
                        ],
                        [
                            11.231748086658081,
                            6.439814704951532
                        ],
                        [
                            11.202276466657704,
                            6.436739237303093
                        ],
                        [
                            11.140384155369375,
                            6.430280514897333
                        ],
                        [
                            11.113512409929907,
                            6.434001148785458
                        ],
                        [
                            11.097079304987473,
                            6.449116514981569
                        ],
                        [
                            11.077442261279883,
                            6.49673639255314
                        ],
                        [
                            11.06059574396281,
                            6.573966771104803
                        ],
                        [
                            11.057391803647963,
                            6.613008265536833
                        ],
                        [
                            11.059045451031798,
                            6.652721663971541
                        ],
                        [
                            11.055944865302008,
                            6.700367377094938
                        ],
                        [
                            11.036721231539122,
                            6.740545685278462
                        ],
                        [
                            11.00261478703422,
                            6.767262476302821
                        ],
                        [
                            10.909390503335477,
                            6.784264070532974
                        ],
                        [
                            10.877454466849219,
                            6.816096676389688
                        ],
                        [
                            10.857404011681052,
                            6.859789074199642
                        ],
                        [
                            10.848205606780803,
                            6.905316026914101
                        ],
                        [
                            10.831875854092615,
                            6.945210280331638
                        ],
                        [
                            10.799112996387707,
                            6.96732783911708
                        ],
                        [
                            10.716947469278143,
                            6.998126976309304
                        ],
                        [
                            10.646977579769024,
                            7.035075545922618
                        ],
                        [
                            10.620622599336192,
                            7.04375727455715
                        ],
                        [
                            10.60253584772349,
                            7.05807155175171
                        ],
                        [
                            10.597161499353442,
                            7.107267612982564
                        ],
                        [
                            10.57866133609403,
                            7.130832025608742
                        ],
                        [
                            10.564191935171932,
                            7.10266838183314
                        ],
                        [
                            10.551789591441548,
                            7.066339893308572
                        ],
                        [
                            10.54331465624593,
                            7.02871941978885
                        ],
                        [
                            10.53742354335164,
                            6.952134963972503
                        ],
                        [
                            10.533186075687448,
                            6.948827567188386
                        ],
                        [
                            10.527501668190078,
                            6.94748405929255
                        ],
                        [
                            10.521197144045322,
                            6.942781481227763
                        ],
                        [
                            10.508898152535709,
                            6.926348294657935
                        ],
                        [
                            10.500733275836785,
                            6.912809117797952
                        ],
                        [
                            10.496599160988028,
                            6.897151182065482
                        ],
                        [
                            10.495979044834577,
                            6.874671909318461
                        ],
                        [
                            10.238423706236196,
                            6.871002949030455
                        ],
                        [
                            10.21082849104792,
                            6.879167793917826
                        ],
                        [
                            10.189847859687868,
                            6.895445810275396
                        ],
                        [
                            10.179409219997845,
                            6.914927876630073
                        ],
                        [
                            10.165043172059395,
                            6.988515126748975
                        ],
                        [
                            10.156878295716165,
                            7.00474146938363
                        ],
                        [
                            10.14292565856969,
                            7.007687002257479
                        ],
                        [
                            10.119464558772888,
                            6.994406192514423
                        ],
                        [
                            9.874621623003842,
                            6.787700500655603
                        ],
                        [
                            9.851160521880274,
                            6.777881957199296
                        ],
                        [
                            9.8317301836759,
                            6.783566329661149
                        ],
                        [
                            9.812299844914548,
                            6.793048996125275
                        ],
                        [
                            9.788528686194729,
                            6.794754367945538
                        ],
                        [
                            9.769821818421054,
                            6.773722099720563
                        ],
                        [
                            9.693979989761088,
                            6.534304745247723
                        ],
                        [
                            9.693030639764016,
                            6.531307839197206
                        ],
                        [
                            9.680524942664517,
                            6.521437622019969
                        ],
                        [
                            9.644805967872095,
                            6.521225520804568
                        ],
                        [
                            9.64481733625741,
                            6.521333524185492
                        ],
                        [
                            9.645024041124723,
                            6.523297262987685
                        ],
                        [
                            9.668381788753347,
                            6.618511030224237
                        ],
                        [
                            9.680370721063975,
                            6.786614458351903
                        ],
                        [
                            9.676650018100673,
                            6.849969779795253
                        ],
                        [
                            9.709619582067385,
                            7.024119437494137
                        ],
                        [
                            9.739695265047821,
                            7.081971090535456
                        ],
                        [
                            9.780312941216811,
                            7.1325106593464564
                        ],
                        [
                            9.830645785485027,
                            7.168425760296476
                        ],
                        [
                            9.87467410537428,
                            7.208991765354788
                        ],
                        [
                            9.881392043511758,
                            7.326581594426174
                        ],
                        [
                            9.920976190635983,
                            7.446393374842154
                        ],
                        [
                            9.876637811758947,
                            7.562484517983902
                        ],
                        [
                            9.774215123124703,
                            7.6532025296749175
                        ],
                        [
                            9.684711541829433,
                            7.7643843944536455
                        ],
                        [
                            9.57123009588147,
                            7.842338176741176
                        ],
                        [
                            9.41837120816682,
                            7.859675492735139
                        ],
                        [
                            9.264788854190117,
                            7.855386603263498
                        ],
                        [
                            9.225411410622288,
                            7.847893364160112
                        ],
                        [
                            9.157715285342986,
                            7.817507621445067
                        ],
                        [
                            9.12608930873169,
                            7.810634763078359
                        ],
                        [
                            9.11410037564954,
                            7.832984696367691
                        ],
                        [
                            9.169394159066648,
                            7.914452565962073
                        ],
                        [
                            9.203914014792932,
                            7.943675656822662
                        ],
                        [
                            9.34902143725233,
                            8.039845496063894
                        ],
                        [
                            9.369588658086334,
                            8.057854864837887
                        ],
                        [
                            9.366281366633277,
                            8.084364802032699
                        ],
                        [
                            9.358633252778391,
                            8.102942277022569
                        ],
                        [
                            9.360390252057687,
                            8.120538258420353
                        ],
                        [
                            9.357289665622385,
                            8.171387849934693
                        ],
                        [
                            9.303856234538195,
                            8.238050389458879
                        ],
                        [
                            9.308093702297374,
                            8.26869449362595
                        ],
                        [
                            9.318635694417884,
                            8.29471353143634
                        ],
                        [
                            9.335172153261917,
                            8.316960413871795
                        ],
                        [
                            9.35997684108258,
                            8.3272181760632
                        ],
                        [
                            9.409276158124495,
                            8.310707637239716
                        ],
                        [
                            9.432530552214965,
                            8.298356803566053
                        ],
                        [
                            9.461055941303359,
                            8.293421697497521
                        ],
                        [
                            9.490821565980612,
                            8.284869155949934
                        ],
                        [
                            9.519243605745794,
                            8.280735287323957
                        ],
                        [
                            9.547458936922244,
                            8.282001284591496
                        ],
                        [
                            9.588283319110484,
                            8.30814950563288
                        ],
                        [
                            9.615465122964101,
                            8.351170278908956
                        ],
                        [
                            9.669828729090927,
                            8.347552843548778
                        ],
                        [
                            9.74506961405198,
                            8.352849662983184
                        ],
                        [
                            9.817519972009011,
                            8.373132656862637
                        ],
                        [
                            9.882115513285065,
                            8.422328695069698
                        ],
                        [
                            9.940303175441375,
                            8.480852072713896
                        ],
                        [
                            10.006035597343024,
                            8.527981174201472
                        ],
                        [
                            10.077349073268591,
                            8.566557433763895
                        ],
                        [
                            10.105357699479834,
                            8.591465490699912
                        ],
                        [
                            10.157654250866772,
                            8.653839128504051
                        ],
                        [
                            10.180288527217076,
                            8.689754208099444
                        ],
                        [
                            10.228864372601723,
                            8.746727377104882
                        ],
                        [
                            10.460271436140168,
                            8.80277042409792
                        ],
                        [
                            10.618504673931216,
                            8.880130224937325
                        ],
                        [
                            10.653024529035243,
                            8.944622159049448
                        ],
                        [
                            10.651784294515599,
                            8.98322454665014
                        ],
                        [
                            10.63896853911457,
                            9.045003626575209
                        ],
                        [
                            10.645893183277394,
                            9.075932221077382
                        ],
                        [
                            10.645996534089102,
                            9.105077484088774
                        ],
                        [
                            10.616954379306307,
                            9.200058777953066
                        ],
                        [
                            10.600624627627933,
                            9.227344099167842
                        ],
                        [
                            10.592253045713097,
                            9.257032229706024
                        ],
                        [
                            10.58109093678165,
                            9.331627185089989
                        ],
                        [
                            10.58884240157784,
                            9.395912707644099
                        ],
                        [
                            10.58202111185395,
                            9.448364135239492
                        ],
                        [
                            10.560420363888625,
                            9.496655858579999
                        ],
                        [
                            10.614060500665135,
                            9.530607332888062
                        ],
                        [
                            10.740771111513684,
                            9.534456995185208
                        ],
                        [
                            10.864277785646683,
                            9.591688800293774
                        ],
                        [
                            10.930320264906584,
                            9.602644144348162
                        ],
                        [
                            10.999153273368748,
                            9.586314474868335
                        ],
                        [
                            11.068606398703515,
                            9.586391984844425
                        ],
                        [
                            11.174853142731195,
                            9.57765859332351
                        ],
                        [
                            11.525942823931521,
                            9.591973003538346
                        ]
                    ]
                ]
            },
            "type": "Feature",
            "properties": {
                "source": "https://simplemaps.com",
                "id": "NGTA",
                "name": "Taraba"
            },
            "id": 9
        }
    ]
}